unified_python_sdk/__init__.py
unified_python_sdk/_hooks/__init__.py
unified_python_sdk/_hooks/sdkhooks.py
unified_python_sdk/_hooks/types.py
unified_python_sdk/_version.py
unified_python_sdk/account.py
unified_python_sdk/accounting.py
unified_python_sdk/activity.py
unified_python_sdk/apicall.py
unified_python_sdk/application.py
unified_python_sdk/applicationstatus.py
unified_python_sdk/ats.py
unified_python_sdk/auth.py
unified_python_sdk/balancesheet.py
unified_python_sdk/basesdk.py
unified_python_sdk/benefit.py
unified_python_sdk/bill.py
unified_python_sdk/branch.py
unified_python_sdk/busy.py
unified_python_sdk/calendar.py
unified_python_sdk/call.py
unified_python_sdk/candidate.py
unified_python_sdk/cashflow.py
unified_python_sdk/category.py
unified_python_sdk/change.py
unified_python_sdk/channel.py
unified_python_sdk/class_.py
unified_python_sdk/collection.py
unified_python_sdk/comment.py
unified_python_sdk/commerce.py
unified_python_sdk/commit.py
unified_python_sdk/company.py
unified_python_sdk/connection.py
unified_python_sdk/contact.py
unified_python_sdk/course.py
unified_python_sdk/creditmemo.py
unified_python_sdk/crm.py
unified_python_sdk/customer.py
unified_python_sdk/deal.py
unified_python_sdk/deduction.py
unified_python_sdk/device.py
unified_python_sdk/document.py
unified_python_sdk/embedding.py
unified_python_sdk/employee.py
unified_python_sdk/enrich.py
unified_python_sdk/environment.py
unified_python_sdk/event.py
unified_python_sdk/expense.py
unified_python_sdk/file.py
unified_python_sdk/genai.py
unified_python_sdk/group.py
unified_python_sdk/hris.py
unified_python_sdk/httpclient.py
unified_python_sdk/instructor.py
unified_python_sdk/integration.py
unified_python_sdk/interview.py
unified_python_sdk/inventory.py
unified_python_sdk/invoice.py
unified_python_sdk/issue.py
unified_python_sdk/item.py
unified_python_sdk/job.py
unified_python_sdk/journal.py
unified_python_sdk/kms.py
unified_python_sdk/lead.py
unified_python_sdk/link.py
unified_python_sdk-0.56.7.dist-info/METADATA
unified_python_sdk-0.56.7.dist-info/WHEEL
unified_python_sdk-0.56.7.dist-info/licenses/LICENSE.md
unified_python_sdk-0.56.7.dist-info/RECORD
